[
  {
    "name": "Kaity Kissed Nails and Designs",
    "category": "beauty",
    "image": "images/nails1.jpg",
    "description": "Bridal nails & designs",
    "page": "vendors/kaity-anderson.html",
    "location": "North Brisbane - Sunshine Coast",
    "featured": true
  },
  {
    "name": "Moments with Koarlie Studios",
    "category": "photography",
    "image": "images/koarlie1.jpg",
    "description": "Capturing magical wedding moments",
    "page": "vendors/moments-with-koarlie.html",
    "location": "North Brisbane - Sunshine Coast",
    "featured": true
  },
  {
    "name": "The Roamed Collective",
    "category": "photography",
    "image": "images/trc1.jpg",
    "description": "Photography & lifestyle",
    "page": "vendors/roamed-collective.html",
    "location": "North Brisbane - Sunshine Coast",
    "featured": true
  },
  {
    "name": "Rosita Flowers",
    "category": "flowers",
    "image": "images/rosita2.jpg",
    "description": "Luxury wedding florals",
    "page": "vendors/rosita-flowers.html",
    "location": "North Brisbane",
    "featured": false
  },
  {
    "name": "Passion For Cakes",
    "category": "cakes",
    "image": "images/cake2.jpg",
    "description": "Custom wedding cakes",
    "page": "vendors/passion-cakes.html",
    "location": "Cairns",
    "featured": false
  }
]
